crownstone_ble/Exceptions.py
crownstone_ble/__init__.py
crownstone_ble/constants/__init__.py
crownstone_ble/core/BleEventBus.py
crownstone_ble/core/CrownstoneBle.py
crownstone_ble/core/__init__.py
crownstone_ble/core/ble_modules/BleHandler.py
crownstone_ble/core/ble_modules/ControlHandler.py
crownstone_ble/core/ble_modules/DebugHandler.py
crownstone_ble/core/ble_modules/DevHandler.py
crownstone_ble/core/ble_modules/MicroappHandler.py
crownstone_ble/core/ble_modules/SetupHandler.py
crownstone_ble/core/ble_modules/StateHandler.py
crownstone_ble/core/ble_modules/__init__.py
crownstone_ble/core/bluetooth_delegates/BleakScanDelegate.py
crownstone_ble/core/bluetooth_delegates/NotificationDelegate.py
crownstone_ble/core/bluetooth_delegates/__init__.py
crownstone_ble/core/container/ScanData.py
crownstone_ble/core/container/ScanDataUtil.py
crownstone_ble/core/container/__init__.py
crownstone_ble/core/modules/Gatherer.py
crownstone_ble/core/modules/ModeChecker.py
crownstone_ble/core/modules/NearestSelector.py
crownstone_ble/core/modules/RssiChecker.py
crownstone_ble/core/modules/StoneAdvertisementTracker.py
crownstone_ble/core/modules/Validator.py
crownstone_ble/core/modules/__init__.py
crownstone_ble/topics/BleTopics.py
crownstone_ble/topics/SystemBleTopics.py
crownstone_ble/topics/__init__.py
crownstone_ble-2.6.2.dist-info/LICENSE-APACHE
crownstone_ble-2.6.2.dist-info/LICENSE-LGPL
crownstone_ble-2.6.2.dist-info/LICENSE-MIT
crownstone_ble-2.6.2.dist-info/METADATA
crownstone_ble-2.6.2.dist-info/WHEEL
crownstone_ble-2.6.2.dist-info/top_level.txt
crownstone_ble-2.6.2.dist-info/RECORD
