Metadata-Version: 2.1
Name: crownstone-ble
Version: 2.6.2
Summary: UNKNOWN
Home-page: https://github.com/crownstone/crownstone-lib-python-ble
Author: Crownstone B.V.
License: UNKNOWN
Platform: UNKNOWN
Classifier: Programming Language :: Python :: 3.7
Requires-Python: >=3.7
Requires-Dist: crownstone-core (~=3.2)
Requires-Dist: bleak (==0.10)
